jk flip_flop/jk.vhdl
--VHDL program for jk flip flop using process (2075 baisakh)
library ieee;
use ieee.std_logic_1164.all;

entity jk_ff is 
    port (
        j, k, clk: in std_logic;
        q, qbar: out std_logic
    );
end jk_ff;

architecture behavioral of jk_ff is 
    signal internal_q, internal_qbar: std_logic;
begin
    process (j, k, clk)
    begin
        if rising_edge(clk) then
            if (j = '1' AND k = '0') then
                internal_q <= '1';
                internal_qbar <= '0';
            elsif (j = '0' and k = '1') then 
                internal_q <= '0';
                internal_qbar <= '1';
            elsif (j = '1' and k = '1') then
                internal_q <= not internal_q;
                internal_qbar <= not internal_qbar;
            end if;
        end if;
    end process;

    -- Assign internal signals to output ports
    q <= internal_q;
    qbar <= internal_qbar;
end behavioral;

jk flip_flop/jk_tb.vhdl
library ieee;
use ieee.std_logic_1164.all;

entity tb_jk_ff is
end tb_jk_ff;

architecture testbench of tb_jk_ff is
    signal j, k, clk, q, qbar: std_logic := '0';

    component jk_ff
        port (
            j, k, clk: in std_logic;
            q, qbar: out std_logic
        );
    end component;

begin
    uut: jk_ff port map(j, k, clk, q, qbar);

    -- Clock process
    process
    begin
        clk <= not clk after 5 ns;
        wait for 10 ns;
    end process;

    -- Stimulus process
    process
    begin
        wait for 20 ns;  -- Initial wait for stability

        j <= '1';
        k <= '0';
        wait for 20 ns;

        j <= '0';
        k <= '1';
        wait for 20 ns;

        j <= '1';
        k <= '1';
        wait for 20 ns;

        -- Add more test cases as needed

        wait;
    end process;

end testbench;

jk flip_flop/result.vcd
$date
  Fri Feb  9 21:24:33 2024
$end
$version
  GHDL v0
$end
$timescale
  1 fs
$end
$scope module standard $end
$upscope $end
$scope module std_logic_1164 $end
$upscope $end
$scope module tb_jk_ff $end
$var reg 1 ! j $end
$var reg 1 " k $end
$var reg 1 # clk $end
$var reg 1 $ q $end
$var reg 1 % qbar $end
$scope module uut $end
$var reg 1 & j $end
$var reg 1 ' k $end
$var reg 1 ( clk $end
$var reg 1 ) q $end
$var reg 1 * qbar $end
$var reg 1 + internal_q $end
$var reg 1 , internal_qbar $end
$upscope $end
$upscope $end
$enddefinitions $end
#0
0!
0"
0#
U$
U%
0&
0'
0(
U)
U*
U+
U,
#5000000
1#
1(
#10000000
#15000000
0#
0(
#20000000
1!
1&
#25000000
1#
1$
0%
1(
1)
0*
1+
0,
#30000000
#35000000
0#
0(
#40000000
0!
1"
0&
1'
#45000000
1#
0$
1%
1(
0)
1*
0+
1,
#50000000
#55000000
0#
0(
#60000000
1!
1&
#65000000
1#
1$
0%
1(
1)
0*
1+
0,
#70000000
#75000000
0#
0(
#80000000
#85000000
1#
0$
1%
1(
0)
1*
0+
1,
#90000000
#95000000
0#
0(
#100000000
#105000000
1#
1$
0%
1(
1)
0*
1+
0,
#110000000
#115000000
0#
0(
#120000000
#125000000
1#
0$
1%
1(
0)
1*
0+
1,
#130000000
#135000000
0#
0(
#140000000
#145000000
1#
1$
0%
1(
1)
0*
1+
0,
#150000000
#155000000
0#
0(
#160000000
#165000000
1#
0$
1%
1(
0)
1*
0+
1,
#170000000
#175000000
0#
0(
#180000000
#185000000
1#
1$
0%
1(
1)
0*
1+
0,
#190000000
#195000000
0#
0(
#200000000
#205000000
1#
0$
1%
1(
0)
1*
0+
1,
#210000000
#215000000
0#
0(
#220000000
#225000000
1#
1$
0%
1(
1)
0*
1+
0,
#230000000
#235000000
0#
0(
#240000000
#245000000
1#
0$
1%
1(
0)
1*
0+
1,
#250000000
#255000000
0#
0(
#260000000
#265000000
1#
1$
0%
1(
1)
0*
1+
0,
#270000000
#275000000
0#
0(
#280000000
#285000000
1#
0$
1%
1(
0)
1*
0+
1,
#290000000
#295000000
0#
0(
#300000000
#305000000
1#
1$
0%
1(
1)
0*
1+
0,
#310000000
#315000000
0#
0(
#320000000
#325000000
1#
0$
1%
1(
0)
1*
0+
1,
#330000000
#335000000
0#
0(
#340000000
#345000000
1#
1$
0%
1(
1)
0*
1+
0,
#350000000
#355000000
0#
0(
#360000000
#365000000
1#
0$
1%
1(
0)
1*
0+
1,
#370000000
#375000000
0#
0(
#380000000
#385000000
1#
1$
0%
1(
1)
0*
1+
0,
#390000000
#395000000
0#
0(
#400000000
#405000000
1#
0$
1%
1(
0)
1*
0+
1,
#410000000
#415000000
0#
0(
#420000000
#425000000
1#
1$
0%
1(
1)
0*
1+
0,
#430000000
#435000000
0#
0(
#440000000
#445000000
1#
0$
1%
1(
0)
1*
0+
1,
#450000000
#455000000
0#
0(
#460000000
#465000000
1#
1$
0%
1(
1)
0*
1+
0,
#470000000
#475000000
0#
0(
#480000000
#485000000
1#
0$
1%
1(
0)
1*
0+
1,
#490000000
#495000000
0#
0(
#500000000
#505000000
1#
1$
0%
1(
1)
0*
1+
0,
#510000000
#515000000
0#
0(
#520000000
#525000000
1#
0$
1%
1(
0)
1*
0+
1,
#530000000
#535000000
0#
0(
#540000000
#545000000
1#
1$
0%
1(
1)
0*
1+
0,
#550000000
#555000000
0#
0(
#560000000
#565000000
1#
0$
1%
1(
0)
1*
0+
1,
#570000000
#575000000
0#
0(
#580000000
#585000000
1#
1$
0%
1(
1)
0*
1+
0,
#590000000
#595000000
0#
0(
#600000000
#605000000
1#
0$
1%
1(
0)
1*
0+
1,
#610000000
#615000000
0#
0(
#620000000
#625000000
1#
1$
0%
1(
1)
0*
1+
0,
#630000000
#635000000
0#
0(
#640000000
#645000000
1#
0$
1%
1(
0)
1*
0+
1,
#650000000
#655000000
0#
0(
#660000000
#665000000
1#
1$
0%
1(
1)
0*
1+
0,
#670000000
#675000000
0#
0(
#680000000
#685000000
1#
0$
1%
1(
0)
1*
0+
1,
#690000000
#695000000
0#
0(
#700000000
#705000000
1#
1$
0%
1(
1)
0*
1+
0,
#710000000
#715000000
0#
0(
#720000000
#725000000
1#
0$
1%
1(
0)
1*
0+
1,
#730000000
#735000000
0#
0(
#740000000
#745000000
1#
1$
0%
1(
1)
0*
1+
0,
#750000000
#755000000
0#
0(
#760000000
#765000000
1#
0$
1%
1(
0)
1*
0+
1,
#770000000
#775000000
0#
0(
#780000000
#785000000
1#
1$
0%
1(
1)
0*
1+
0,
#790000000
#795000000
0#
0(
#800000000
#805000000
1#
0$
1%
1(
0)
1*
0+
1,
#810000000
#815000000
0#
0(
#820000000
#825000000
1#
1$
0%
1(
1)
0*
1+
0,
#830000000
#835000000
0#
0(
#840000000
#845000000
1#
0$
1%
1(
0)
1*
0+
1,
#850000000
#855000000
0#
0(
#860000000
#865000000
1#
1$
0%
1(
1)
0*
1+
0,
#870000000
#875000000
0#
0(
#880000000
#885000000
1#
0$
1%
1(
0)
1*
0+
1,
#890000000
#895000000
0#
0(
#900000000
#905000000
1#
1$
0%
1(
1)
0*
1+
0,
#910000000
#915000000
0#
0(
#920000000
#925000000
1#
0$
1%
1(
0)
1*
0+
1,
#930000000
#935000000
0#
0(
#940000000
#945000000
1#
1$
0%
1(
1)
0*
1+
0,
#950000000
#955000000
0#
0(
#960000000
#965000000
1#
0$
1%
1(
0)
1*
0+
1,
#970000000
#975000000
0#
0(
#980000000
#985000000
1#
1$
0%
1(
1)
0*
1+
0,
#990000000
#995000000
0#
0(
#1000000000
#1005000000
1#
0$
1%
1(
0)
1*
0+
1,
#1010000000
#1015000000
0#
0(
#1020000000
#1025000000
1#
1$
0%
1(
1)
0*
1+
0,
#1030000000
#1035000000
0#
0(
#1040000000
#1045000000
1#
0$
1%
1(
0)
1*
0+
1,
#1050000000
#1055000000
0#
0(
#1060000000
#1065000000
1#
1$
0%
1(
1)
0*
1+
0,
#1070000000
#1075000000
0#
0(
#1080000000
#1085000000
1#
0$
1%
1(
0)
1*
0+
1,
#1090000000
#1095000000
0#
0(
#1100000000
#1105000000
1#
1$
0%
1(
1)
0*
1+
0,
#1110000000
#1115000000
0#
0(
#1120000000
#1125000000
1#
0$
1%
1(
0)
1*
0+
1,
#1130000000
#1135000000
0#
0(
#1140000000
#1145000000
1#
1$
0%
1(
1)
0*
1+
0,
#1150000000
#1155000000
0#
0(
#1160000000
#1165000000
1#
0$
1%
1(
0)
1*
0+
1,
#1170000000
#1175000000
0#
0(
#1180000000
#1185000000
1#
1$
0%
1(
1)
0*
1+
0,
#1190000000
#1195000000
0#
0(
#1200000000
#1205000000
1#
0$
1%
1(
0)
1*
0+
1,
#1210000000
#1215000000
0#
0(
#1220000000
#1225000000
1#
1$
0%
1(
1)
0*
1+
0,
#1230000000
#1235000000
0#
0(
#1240000000
#1245000000
1#
0$
1%
1(
0)
1*
0+
1,
#1250000000
#1255000000
0#
0(
#1260000000
#1265000000
1#
1$
0%
1(
1)
0*
1+
0,
#1270000000
#1275000000
0#
0(
#1280000000
#1285000000
1#
0$
1%
1(
0)
1*
0+
1,
#1290000000
#1295000000
0#
0(
#1300000000
#1305000000
1#
1$
0%
1(
1)
0*
1+
0,
#1310000000
#1315000000
0#
0(
#1320000000
#1325000000
1#
0$
1%
1(
0)
1*
0+
1,
#1330000000
#1335000000
0#
0(
#1340000000
#1345000000
1#
1$
0%
1(
1)
0*
1+
0,
#1350000000
#1355000000
0#
0(
#1360000000
#1365000000
1#
0$
1%
1(
0)
1*
0+
1,
#1370000000
#1375000000
0#
0(
#1380000000
#1385000000
1#
1$
0%
1(
1)
0*
1+
0,
#1390000000
#1395000000
0#
0(
#1400000000
#1405000000
1#
0$
1%
1(
0)
1*
0+
1,
#1410000000
#1415000000
0#
0(
#1420000000
#1425000000
1#
1$
0%
1(
1)
0*
1+
0,
#1430000000
#1435000000
0#
0(
#1440000000
#1445000000
1#
0$
1%
1(
0)
1*
0+
1,
#1450000000
#1455000000
0#
0(
#1460000000
#1465000000
1#
1$
0%
1(
1)
0*
1+
0,
#1470000000
#1475000000
0#
0(
#1480000000
#1485000000
1#
0$
1%
1(
0)
1*
0+
1,
#1490000000
#1495000000
0#
0(
#1500000000
#1505000000
1#
1$
0%
1(
1)
0*
1+
0,
#1510000000
#1515000000
0#
0(
#1520000000
#1525000000
1#
0$
1%
1(
0)
1*
0+
1,
#1530000000
#1535000000
0#
0(
#1540000000
#1545000000
1#
1$
0%
1(
1)
0*
1+
0,
#1550000000
#1555000000
0#
0(
#1560000000
#1565000000
1#
0$
1%
1(
0)
1*
0+
1,
#1570000000
#1575000000
0#
0(
#1580000000
#1585000000
1#
1$
0%
1(
1)
0*
1+
0,
#1590000000
#1595000000
0#
0(
#1600000000
#1605000000
1#
0$
1%
1(
0)
1*
0+
1,
#1610000000
#1615000000
0#
0(
#1620000000
#1625000000
1#
1$
0%
1(
1)
0*
1+
0,
#1630000000
#1635000000
0#
0(
#1640000000
#1645000000
1#
0$
1%
1(
0)
1*
0+
1,
#1650000000
#1655000000
0#
0(
#1660000000
#1665000000
1#
1$
0%
1(
1)
0*
1+
0,
#1670000000
#1675000000
0#
0(
#1680000000
#1685000000
1#
0$
1%
1(
0)
1*
0+
1,
#1690000000
#1695000000
0#
0(
#1700000000
#1705000000
1#
1$
0%
1(
1)
0*
1+
0,
#1710000000
#1715000000
0#
0(
#1720000000
#1725000000
1#
0$
1%
1(
0)
1*
0+
1,
#1730000000
#1735000000
0#
0(
#1740000000
#1745000000
1#
1$
0%
1(
1)
0*
1+
0,
#1750000000
#1755000000
0#
0(
#1760000000
#1765000000
1#
0$
1%
1(
0)
1*
0+
1,
#1770000000
#1775000000
0#
0(
#1780000000
#1785000000
1#
1$
0%
1(
1)
0*
1+
0,
#1790000000
#1795000000
0#
0(
#1800000000
#1805000000
1#
0$
1%
1(
0)
1*
0+
1,
#1810000000
#1815000000
0#
0(
#1820000000
#1825000000
1#
1$
0%
1(
1)
0*
1+
0,
#1830000000
#1835000000
0#
0(
#1840000000
#1845000000
1#
0$
1%
1(
0)
1*
0+
1,
#1850000000
#1855000000
0#
0(
#1860000000
#1865000000
1#
1$
0%
1(
1)
0*
1+
0,
#1870000000
#1875000000
0#
0(
#1880000000
#1885000000
1#
0$
1%
1(
0)
1*
0+
1,
#1890000000
#1895000000
0#
0(
#1900000000
#1905000000
1#
1$
0%
1(
1)
0*
1+
0,
#1910000000
#1915000000
0#
0(
#1920000000
#1925000000
1#
0$
1%
1(
0)
1*
0+
1,
#1930000000
#1935000000
0#
0(
#1940000000
#1945000000
1#
1$
0%
1(
1)
0*
1+
0,
#1950000000
#1955000000
0#
0(
#1960000000
#1965000000
1#
0$
1%
1(
0)
1*
0+
1,
#1970000000
#1975000000
0#
0(
#1980000000
#1985000000
1#
1$
0%
1(
1)
0*
1+
0,
#1990000000
#1995000000
0#
0(
#2000000000
#2005000000
1#
0$
1%
1(
0)
1*
0+
1,
#2010000000
#2015000000
0#
0(
#2020000000
#2025000000
1#
1$
0%
1(
1)
0*
1+
0,
#2030000000
#2035000000
0#
0(
#2040000000
#2045000000
1#
0$
1%
1(
0)
1*
0+
1,
#2050000000
#2055000000
0#
0(
#2060000000
#2065000000
1#
1$
0%
1(
1)
0*
1+
0,
#2070000000
#2075000000
0#
0(
#2080000000
#2085000000
1#
0$
1%
1(
0)
1*
0+
1,
#2090000000
#2095000000
0#
0(
#2100000000
#2105000000
1#
1$
0%
1(
1)
0*
1+
0,
#2110000000
#2115000000
0#
0(
#2120000000
#2125000000
1#
0$
1%
1(
0)
1*
0+
1,
#2130000000
#2135000000
0#
0(
#2140000000
#2145000000
1#
1$
0%
1(
1)
0*
1+
0,
#2150000000
#2155000000
0#
0(
#2160000000
#2165000000
1#
0$
1%
1(
0)
1*
0+
1,
#2170000000
#2175000000
0#
0(
#2180000000
#2185000000
1#
1$
0%
1(
1)
0*
1+
0,
#2190000000
#2195000000
0#
0(
#2200000000
#2205000000
1#
0$
1%
1(
0)
1*
0+
1,
#2210000000
#2215000000
0#
0(
#2220000000
#2225000000
1#
1$
0%
1(
1)
0*
1+
0,
#2230000000
#2235000000
0#
0(
#2240000000
#2245000000
1#
0$
1%
1(
0)
1*
0+
1,
#2250000000
#2255000000
0#
0(
#2260000000
#2265000000
1#
1$
0%
1(
1)
0*
1+
0,
#2270000000
#2275000000
0#
0(
#2280000000
#2285000000
1#
0$
1%
1(
0)
1*
0+
1,
#2290000000
#2295000000
0#
0(
#2300000000
#2305000000
1#
1$
0%
1(
1)
0*
1+
0,
#2310000000
#2315000000
0#
0(
#2320000000
#2325000000
1#
0$
1%
1(
0)
1*
0+
1,
#2330000000
#2335000000
0#
0(
#2340000000
#2345000000
1#
1$
0%
1(
1)
0*
1+
0,
#2350000000
#2355000000
0#
0(
#2360000000
#2365000000
1#
0$
1%
1(
0)
1*
0+
1,
#2370000000
#2375000000
0#
0(
#2380000000
#2385000000
1#
1$
0%
1(
1)
0*
1+
0,
#2390000000
#2395000000
0#
0(
#2400000000
#2405000000
1#
0$
1%
1(
0)
1*
0+
1,
#2410000000
#2415000000
0#
0(
#2420000000
#2425000000
1#
1$
0%
1(
1)
0*
1+
0,
#2430000000
#2435000000
0#
0(
#2440000000
#2445000000
1#
0$
1%
1(
0)
1*
0+
1,
#2450000000
#2455000000
0#
0(
#2460000000
#2465000000
1#
1$
0%
1(
1)
0*
1+
0,
#2470000000
#2475000000
0#
0(
#2480000000
#2485000000
1#
0$
1%
1(
0)
1*
0+
1,
#2490000000
#2495000000
0#
0(
#2500000000
#2505000000
1#
1$
0%
1(
1)
0*
1+
0,
#2510000000
#2515000000
0#
0(
#2520000000
#2525000000
1#
0$
1%
1(
0)
1*
0+
1,
#2530000000
#2535000000
0#
0(
#2540000000
#2545000000
1#
1$
0%
1(
1)
0*
1+
0,
#2550000000
#2555000000
0#
0(
#2560000000
#2565000000
1#
0$
1%
1(
0)
1*
0+
1,
#2570000000
#2575000000
0#
0(
#2580000000
#2585000000
1#
1$
0%
1(
1)
0*
1+
0,
#2590000000
#2595000000
0#
0(
#2600000000
#2605000000
1#
0$
1%
1(
0)
1*
0+
1,
#2610000000
#2615000000
0#
0(
#2620000000
#2625000000
1#
1$
0%
1(
1)
0*
1+
0,
#2630000000
#2635000000
0#
0(
#2640000000
#2645000000
1#
0$
1%
1(
0)
1*
0+
1,
#2650000000
#2655000000
0#
0(
#2660000000
#2665000000
1#
1$
0%
1(
1)
0*
1+
0,
#2670000000
#2675000000
0#
0(
#2680000000
#2685000000
1#
0$
1%
1(
0)
1*
0+
1,
#2690000000
#2695000000
0#
0(
#2700000000
#2705000000
1#
1$
0%
1(
1)
0*
1+
0,
#2710000000
#2715000000
0#
0(
#2720000000
#2725000000
1#
0$
1%
1(
0)
1*
0+
1,
#2730000000
#2735000000
0#
0(
#2740000000
#2745000000
1#
1$
0%
1(
1)
0*
1+
0,
#2750000000
#2755000000
0#
0(
#2760000000
#2765000000
1#
0$
1%
1(
0)
1*
0+
1,
#2770000000
#2775000000
0#
0(
#2780000000
#2785000000
1#
1$
0%
1(
1)
0*
1+
0,
#2790000000
#2795000000
0#
0(
#2800000000
#2805000000
1#
0$
1%
1(
0)
1*
0+
1,
#2810000000
#2815000000
0#
0(
#2820000000
#2825000000
1#
1$
0%
1(
1)
0*
1+
0,
#2830000000
#2835000000
0#
0(
#2840000000
#2845000000
1#
0$
1%
1(
0)
1*
0+
1,
#2850000000
#2855000000
0#
0(
#2860000000
#2865000000
1#
1$
0%
1(
1)
0*
1+
0,
#2870000000
#2875000000
0#
0(
#2880000000
#2885000000
1#
0$
1%
1(
0)
1*
0+
1,
#2890000000
#2895000000
0#
0(
#2900000000
#2905000000
1#
1$
0%
1(
1)
0*
1+
0,
#2910000000
#2915000000
0#
0(
#2920000000
#2925000000
1#
0$
1%
1(
0)
1*
0+
1,
#2930000000
#2935000000
0#
0(
#2940000000
#2945000000
1#
1$
0%
1(
1)
0*
1+
0,
#2950000000
#2955000000
0#
0(
#2960000000
#2965000000
1#
0$
1%
1(
0)
1*
0+
1,
#2970000000
#2975000000
0#
0(
#2980000000
#2985000000
1#
1$
0%
1(
1)
0*
1+
0,
#2990000000
#2995000000
0#
0(
#3000000000
#3005000000
1#
0$
1%
1(
0)
1*
0+
1,
#3010000000
#3015000000
0#
0(
#3020000000
#3025000000
1#
1$
0%
1(
1)
0*
1+
0,
#3030000000
#3035000000
0#
0(
#3040000000
#3045000000
1#
0$
1%
1(
0)
1*
0+
1,
#3050000000
#3055000000
0#
0(
#3060000000
#3065000000
1#
1$
0%
1(
1)
0*
1+
0,
#3070000000
#3075000000
0#
0(
#3080000000
#3085000000
1#
0$
1%
1(
0)
1*
0+
1,
#3090000000
#3095000000
0#
0(
#3100000000
#3105000000
1#
1$
0%
1(
1)
0*
1+
0,
#3110000000
#3115000000
0#
0(
#3120000000
#3125000000
1#
0$
1%
1(
0)
1*
0+
1,
#3130000000
#3135000000
0#
0(
#3140000000
#3145000000
1#
1$
0%
1(
1)
0*
1+
0,
#3150000000
#3155000000
0#
0(
#3160000000
#3165000000
1#
0$
1%
1(
0)
1*
0+
1,
#3170000000
#3175000000
0#
0(
#3180000000
#3185000000
1#
1$
0%
1(
1)
0*
1+
0,
#3190000000
#3195000000
0#
0(
#3200000000
#3205000000
1#
0$
1%
1(
0)
1*
0+
1,
#3210000000
#3215000000
0#
0(
#3220000000
#3225000000
1#
1$
0%
1(
1)
0*
1+
0,
#3230000000
#3235000000
0#
0(
#3240000000
#3245000000
1#
0$
1%
1(
0)
1*
0+
1,
#3250000000
#3255000000
0#
0(
#3260000000
#3265000000
1#
1$
0%
1(
1)
0*
1+
0,
#3270000000
#3275000000
0#
0(
#3280000000
#3285000000
1#
0$
1%
1(
0)
1*
0+
1,
#3290000000
#3295000000
0#
0(
#3300000000
#3305000000
1#
1$
0%
1(
1)
0*
1+
0,
#3310000000
#3315000000
0#
0(
#3320000000
#3325000000
1#
0$
1%
1(
0)
1*
0+
1,
#3330000000
#3335000000
0#
0(
#3340000000
#3345000000
1#
1$
0%
1(
1)
0*
1+
0,
#3350000000
#3355000000
0#
0(
#3360000000
#3365000000
1#
0$
1%
1(
0)
1*
0+
1,
#3370000000
#3375000000
0#
0(
#3380000000
#3385000000
1#
1$
0%
1(
1)
0*
1+
0,
#3390000000
#3395000000
0#
0(
#3400000000
#3405000000
1#
0$
1%
1(
0)
1*
0+
1,
#3410000000
#3415000000
0#
0(
#3420000000
#3425000000
1#
1$
0%
1(
1)
0*
1+
0,
#3430000000
#3435000000
0#
0(
#3440000000
#3445000000
1#
0$
1%
1(
0)
1*
0+
1,
#3450000000
#3455000000
0#
0(
#3460000000
#3465000000
1#
1$
0%
1(
1)
0*
1+
0,
#3470000000
#3475000000
0#
0(
#3480000000
#3485000000
1#
0$
1%
1(
0)
1*
0+
1,
#3490000000
#3495000000
0#
0(
#3500000000
#3505000000
1#
1$
0%
1(
1)
0*
1+
0,
#3510000000
#3515000000
0#
0(
#3520000000
#3525000000
1#
0$
1%
1(
0)
1*
0+
1,
#3530000000
#3535000000
0#
0(
#3540000000
#3545000000
1#
1$
0%
1(
1)
0*
1+
0,
#3550000000
#3555000000
0#
0(
#3560000000
#3565000000
1#
0$
1%
1(
0)
1*
0+
1,
#3570000000
#3575000000
0#
0(
#3580000000
#3585000000
1#
1$
0%
1(
1)
0*
1+
0,
#3590000000
#3595000000
0#
0(
#3600000000
#3605000000
1#
0$
1%
1(
0)
1*
0+
1,
#3610000000
#3615000000
0#
0(
#3620000000
#3625000000
1#
1$
0%
1(
1)
0*
1+
0,
#3630000000
#3635000000
0#
0(
#3640000000
#3645000000
1#
0$
1%
1(
0)
1*
0+
1,
#3650000000
#3655000000
0#
0(
#3660000000
#3665000000
1#
1$
0%
1(
1)
0*
1+
0,
#3670000000
#3675000000
0#
0(
#3680000000
#3685000000
1#
0$
1%
1(
0)
1*
0+
1,
#3690000000
#3695000000
0#
0(
#3700000000
#3705000000
1#
1$
0%
1(
1)
0*
1+
0,
#3710000000
#3715000000
0#
0(
#3720000000
#3725000000
1#
0$
1%
1(
0)
1*
0+
1,
#3730000000
#3735000000
0#
0(
#3740000000
#3745000000
1#
1$
0%
1(
1)
0*
1+
0,
#3750000000
#3755000000
0#
0(
#3760000000
#3765000000
1#
0$
1%
1(
0)
1*
0+
1,
#3770000000
#3775000000
0#
0(
#3780000000
#3785000000
1#
1$
0%
1(
1)
0*
1+
0,
#3790000000
#3795000000
0#
0(
#3800000000
#3805000000
1#
0$
1%
1(
0)
1*
0+
1,
#3810000000
#3815000000
0#
0(
#3820000000
#3825000000
1#
1$
0%
1(
1)
0*
1+
0,
#3830000000
#3835000000
0#
0(
#3840000000
#3845000000
1#
0$
1%
1(
0)
1*
0+
1,
#3850000000
#3855000000
0#
0(
#3860000000
#3865000000
1#
1$
0%
1(
1)
0*
1+
0,
#3870000000
#3875000000
0#
0(
#3880000000
#3885000000
1#
0$
1%
1(
0)
1*
0+
1,
#3890000000
#3895000000
0#
0(
#3900000000
#3905000000
1#
1$
0%
1(
1)
0*
1+
0,
#3910000000
#3915000000
0#
0(
#3920000000
#3925000000
1#
0$
1%
1(
0)
1*
0+
1,
#3930000000
#3935000000
0#
0(
#3940000000
#3945000000
1#
1$
0%
1(
1)
0*
1+
0,
#3950000000
#3955000000
0#
0(
#3960000000
#3965000000
1#
0$
1%
1(
0)
1*
0+
1,
#3970000000
#3975000000
0#
0(
#3980000000
#3985000000
1#
1$
0%
1(
1)
0*
1+
0,
#3990000000
#3995000000
0#
0(
#4000000000
#4005000000
1#
0$
1%
1(
0)
1*
0+
1,
#4010000000
#4015000000
0#
0(
#4020000000
#4025000000
1#
1$
0%
1(
1)
0*
1+
0,
#4030000000
#4035000000
0#
0(
#4040000000
#4045000000
1#
0$
1%
1(
0)
1*
0+
1,
#4050000000
#4055000000
0#
0(
#4060000000
#4065000000
1#
1$
0%
1(
1)
0*
1+
0,
#4070000000
#4075000000
0#
0(
#4080000000
#4085000000
1#
0$
1%
1(
0)
1*
0+
1,
#4090000000
#4095000000
0#
0(
#4100000000
#4105000000
1#
1$
0%
1(
1)
0*
1+
0,
#4110000000
#4115000000
0#
0(
#4120000000
#4125000000
1#
0$
1%
1(
0)
1*
0+
1,
#4130000000
#4135000000
0#
0(
#4140000000
#4145000000
1#
1$
0%
1(
1)
0*
1+
0,
#4150000000
#4155000000
0#
0(
#4160000000
#4165000000
1#
0$
1%
1(
0)
1*
0+
1,
#4170000000
#4175000000
0#
0(
#4180000000
#4185000000
1#
1$
0%
1(
1)
0*
1+
0,
#4190000000
#4195000000
0#
0(
#4200000000
#4205000000
1#
0$
1%
1(
0)
1*
0+
1,
#4210000000
#4215000000
0#
0(
#4220000000
#4225000000
1#
1$
0%
1(
1)
0*
1+
0,
#4230000000
#4235000000
0#
0(
#4240000000
#4245000000
1#
0$
1%
1(
0)
1*
0+
1,
#4250000000
#4255000000
0#
0(
#4260000000
#4265000000
1#
1$
0%
1(
1)
0*
1+
0,
#4270000000
#4275000000
0#
0(
#4280000000
#4285000000
1#
0$
1%
1(
0)
1*
0+
1,
#4290000000
#4295000000
0#
0(
#4300000000
#4305000000
1#
1$
0%
1(
1)
0*
1+
0,
#4310000000
#4315000000
0#
0(
#4320000000
#4325000000
1#
0$
1%
1(
0)
1*
0+
1,
#4330000000
#4335000000
0#
0(
#4340000000
#4345000000
1#
1$
0%
1(
1)
0*
1+
0,
#4350000000
#4355000000
0#
0(
#4360000000
#4365000000
1#
0$
1%
1(
0)
1*
0+
1,
#4370000000
#4375000000
0#
0(
#4380000000
#4385000000
1#
1$
0%
1(
1)
0*
1+
0,
#4390000000
#4395000000
0#
0(
#4400000000
#4405000000
1#
0$
1%
1(
0)
1*
0+
1,
#4410000000
#4415000000
0#
0(
#4420000000
#4425000000
1#
1$
0%
1(
1)
0*
1+
0,
#4430000000
#4435000000
0#
0(
#4440000000
#4445000000
1#
0$
1%
1(
0)
1*
0+
1,
#4450000000
#4455000000
0#
0(
#4460000000
#4465000000
1#
1$
0%
1(
1)
0*
1+
0,
#4470000000
#4475000000
0#
0(
#4480000000
#4485000000
1#
0$
1%
1(
0)
1*
0+
1,
#4490000000
#4495000000
0#
0(
#4500000000
#4505000000
1#
1$
0%
1(
1)
0*
1+
0,
#4510000000
#4515000000
0#
0(
#4520000000
#4525000000
1#
0$
1%
1(
0)
1*
0+
1,
#4530000000
#4535000000
0#
0(
#4540000000
#4545000000
1#
1$
0%
1(
1)
0*
1+
0,
#4550000000
#4555000000
0#
0(
#4560000000
#4565000000
1#
0$
1%
1(
0)
1*
0+
1,
#4570000000
#4575000000
0#
0(
#4580000000
#4585000000
1#
1$
0%
1(
1)
0*
1+
0,
#4590000000
#4595000000
0#
0(
#4600000000
#4605000000
1#
0$
1%
1(
0)
1*
0+
1,
#4610000000
#4615000000
0#
0(
#4620000000
#4625000000
1#
1$
0%
1(
1)
0*
1+
0,
#4630000000
#4635000000
0#
0(
#4640000000
#4645000000
1#
0$
1%
1(
0)
1*
0+
1,
#4650000000
#4655000000
0#
0(
#4660000000
#4665000000
1#
1$
0%
1(
1)
0*
1+
0,
#4670000000
#4675000000
0#
0(
#4680000000
#4685000000
1#
0$
1%
1(
0)
1*
0+
1,
#4690000000
#4695000000
0#
0(
#4700000000
#4705000000
1#
1$
0%
1(
1)
0*
1+
0,
#4710000000
#4715000000
0#
0(
#4720000000
#4725000000
1#
0$
1%
1(
0)
1*
0+
1,
#4730000000
#4735000000
0#
0(
#4740000000
#4745000000
1#
1$
0%
1(
1)
0*
1+
0,
#4750000000
#4755000000
0#
0(
#4760000000
#4765000000
1#
0$
1%
1(
0)
1*
0+
1,
#4770000000
#4775000000
0#
0(
#4780000000
#4785000000
1#
1$
0%
1(
1)
0*
1+
0,
#4790000000
#4795000000
0#
0(
#4800000000
#4805000000
1#
0$
1%
1(
0)
1*
0+
1,
#4810000000
#4815000000
0#
0(
#4820000000
#4825000000
1#
1$
0%
1(
1)
0*
1+
0,
#4830000000
#4835000000
0#
0(
#4840000000
#4845000000
1#
0$
1%
1(
0)
1*
0+
1,
#4850000000
#4855000000
0#
0(
#4860000000
#4865000000
1#
1$
0%
1(
1)
0*
1+
0,
#4870000000
#4875000000
0#
0(
#4880000000
#4885000000
1#
0$
1%
1(
0)
1*
0+
1,
#4890000000
#4895000000
0#
0(
#4900000000
#4905000000
1#
1$
0%
1(
1)
0*
1+
0,
#4910000000
#4915000000
0#
0(
#4920000000
#4925000000
1#
0$
1%
1(
0)
1*
0+
1,
#4930000000
#4935000000
0#
0(
#4940000000
#4945000000
1#
1$
0%
1(
1)
0*
1+
0,
#4950000000
#4955000000
0#
0(
#4960000000
#4965000000
1#
0$
1%
1(
0)
1*
0+
1,
#4970000000
#4975000000
0#
0(
#4980000000
#4985000000
1#
1$
0%
1(
1)
0*
1+
0,
#4990000000
#4995000000
0#
0(
#5000000000
#5005000000
1#
0$
1%
1(
0)
1*
0+
1,
#5010000000
#5015000000
0#
0(
#5020000000
#5025000000
1#
1$
0%
1(
1)
0*
1+
0,
#5030000000
#5035000000
0#
0(
#5040000000
#5045000000
1#
0$
1%
1(
0)
1*
0+
1,
#5050000000
#5055000000
0#
0(
#5060000000
#5065000000
1#
1$
0%
1(
1)
0*
1+
0,
#5070000000
#5075000000
0#
0(
#5080000000
#5085000000
1#
0$
1%
1(
0)
1*
0+
1,
#5090000000
#5095000000
0#
0(
#5100000000
#5105000000
1#
1$
0%
1(
1)
0*
1+
0,
#5110000000
#5115000000
0#
0(
#5120000000
#5125000000
1#
0$
1%
1(
0)
1*
0+
1,
#5130000000
#5135000000
0#
0(
#5140000000
#5145000000
1#
1$
0%
1(
1)
0*
1+
0,
#5150000000
#5155000000
0#
0(
#5160000000
#5165000000
1#
0$
1%
1(
0)
1*
0+
1,
#5170000000
#5175000000
0#
0(
#5180000000
#5185000000
1#
1$
0%
1(
1)
0*
1+
0,
#5190000000
#5195000000
0#
0(
#5200000000
#5205000000
1#
0$
1%
1(
0)
1*
0+
1,
#5210000000
