LCM/lcm.vhdl
-- lcm of two number as a finite state machine(2074 bhadra)


library IEEE;
use IEEE.STD_LOGIC_1164.ALL;

entity LCM is
    Port (
        RESET : in  STD_LOGIC;
        CLK : in  STD_LOGIC;
        NUM1 : in  INTEGER;
        NUM2 : in  INTEGER;
        LCM_OUT : out  INTEGER
    );
end LCM;

architecture Behavioral of LCM is
    type state is (START, INPUT, OUTPUT);
    signal PS, NS : state;
    signal X, Y, LCM_temp : INTEGER := 0;

    function calculate_GCD(a, b : INTEGER) return INTEGER is
        variable temp_a, temp_b, temp_gcd : INTEGER := 0;
    begin
        temp_a := a;
        temp_b := b;
        while temp_b /= 0 loop
            temp_gcd := temp_a;
            temp_a := temp_b;
            temp_b := temp_gcd rem temp_b;
        end loop;
        return temp_a;
    end function;

begin
    seq_proc : process(CLK, RESET)
    begin
        if (RESET = '1') then 
            PS <= START;
        elsif (rising_edge(CLK)) then 
            PS <= NS;
        end if;
    end process seq_proc;

    comb_proc : process(NUM1, NUM2, PS)
    begin
        case PS is
            when START =>
                LCM_OUT <= 0;
                NS <= INPUT;

            when INPUT =>
                X <= NUM1;
                Y <= NUM2;
                LCM_temp <= (X / calculate_GCD(X, Y)) * Y;  -- Calculate LCM
                NS <= OUTPUT;

            when OUTPUT =>
                LCM_OUT <= LCM_temp;
                NS <= INPUT;

            when others =>
                LCM_OUT <= 0;
                NS <= INPUT;
        end case;
    end process comb_proc;

end Behavioral;

LCM/lcm_tb.vhdl

library IEEE;
use IEEE.STD_LOGIC_1164.ALL;

entity tb_LCM is
end tb_LCM;

architecture testbench of tb_LCM is
    signal RESET, CLK: STD_LOGIC := '0';
    signal NUM1, NUM2, LCM_OUT: INTEGER := 0;

    component LCM
        Port (
            RESET : in  STD_LOGIC;
            CLK : in  STD_LOGIC;
            NUM1 : in  INTEGER;
            NUM2 : in  INTEGER;
            LCM_OUT : out  INTEGER
        );
    end component;

begin
    uut: LCM port map(RESET, CLK, NUM1, NUM2, LCM_OUT);

    -- Clock process
    process
    begin
        while now < 100 ns loop
            CLK <= '0';
            wait for 5 ns;
            CLK <= '1';
            wait for 5 ns;
        end loop;
        wait;
    end process;

    -- Stimulus process
    process
    begin
        wait for 10 ns;  -- Initial wait for stability

        RESET <= '1';
        NUM1 <= 6;
        NUM2 <= 8;
        wait for 20 ns;

        RESET <= '0';
        wait for 20 ns;

        NUM1 <= 12;
        NUM2 <= 18;
        wait for 20 ns;

        NUM1 <= 0;
        NUM2 <= 5;
        wait for 20 ns;

        -- Add more test cases as needed

        wait;
    end process;

end testbench;

LCM/result.vcd
$date
  Sat Feb 10 10:27:59 2024
$end
$version
  GHDL v0
$end
$timescale
  1 fs
$end
$scope module standard $end
$upscope $end
$scope module std_logic_1164 $end
$upscope $end
$scope module tb_lcm $end
$var reg 1 ! reset $end
$var reg 1 " clk $end
$var integer 32 # num1 $end
$var integer 32 $ num2 $end
$var integer 32 % lcm_out $end
$scope module uut $end
$var reg 1 & reset $end
$var reg 1 ' clk $end
$var integer 32 ( num1 $end
$var integer 32 ) num2 $end
$var integer 32 * lcm_out $end
$comment ps is not handled $end
$comment ns is not handled $end
$var integer 32 + x $end
$var integer 32 , y $end
$var integer 32 - lcm_temp $end
$upscope $end
$upscope $end
$enddefinitions $end
#0
0!
0"
b0 #
b0 $
b0 %
0&
0'
b0 (
b0 )
b0 *
b0 +
b0 ,
b0 -
#5000000
1"
1'
#10000000
1!
0"
b110 #
b1000 $
1&
0'
b110 (
b1000 )
b110 +
b1000 ,
#15000000
1"
1'
#20000000
0"
0'
#25000000
1"
1'
#30000000
0!
0"
0&
0'
#35000000
1"
1'
b11000 -
#40000000
0"
0'
#45000000
1"
b11000 %
1'
b11000 *
#50000000
0"
b1100 #
b10010 $
0'
b1100 (
b10010 )
#55000000
1"
1'
b1100 +
b10010 ,
#60000000
0"
0'
#65000000
1"
1'
#70000000
0"
b0 #
b101 $
0'
b0 (
b101 )
#75000000
1"
1'
b0 +
b101 ,
b100100 -
#80000000
0"
0'
#85000000
1"
b100100 %
1'
b100100 *
#90000000
0"
0'
#95000000
1"
1'
b0 -
