elevator_control/elevator.vhdl
---elevator control unit using vhdl (2078 baisakh)
library ieee;
use ieee.std_logic_1164.all;
use ieee.numeric_std.all;

entity elevator_control is 
  port(
    clk: in std_logic;
    reset: in std_logic;
    floor_up: in std_logic;
    floor_down: in std_logic;
    floor_num: out std_logic_vector(3 downto 0)
  );
end elevator_control;

architecture behavioral of elevator_control is
  type state_type is (idle, up, down);
  signal curr_state, next_state: state_type;
  signal curr_floor: integer range 0 to 15;
begin
  process(clk, reset)
  begin
    if reset = '1' then 
      curr_state <= idle;
      curr_floor <= 0;
    elsif clk'event and clk = '1' then
      curr_state <= next_state;
      curr_floor <= curr_floor + 1;
    end if;
  end process;

  process(curr_state, floor_up, floor_down)
  begin
    case curr_state is 
      when idle =>
        if floor_up = '1' then 
          next_state <= up;
        elsif floor_down = '1' then
          next_state <= down;
        else
          next_state <= idle;
        end if;
      when up =>
        if floor_down = '1' then 
          next_state <= down;
        else
          next_state <= up;
        end if;
      when down =>
        if floor_up = '1' then 
          next_state <= up;
        else
          next_state <= down;
        end if;
    end case;
  end process;

  floor_num <= std_logic_vector(to_unsigned(curr_floor, 4));
end behavioral;

elevator_control/elevator_tb.vhdl
library ieee;
use ieee.std_logic_1164.all;

entity elevator_control_tb is
end elevator_control_tb;

architecture tb_architecture of elevator_control_tb is
  signal clk, reset, floor_up, floor_down : std_logic := '0';
  signal floor_num_out : std_logic_vector(3 downto 0);

  component elevator_control
    port (
      clk       : in std_logic;
      reset     : in std_logic;
      floor_up  : in std_logic;
      floor_down: in std_logic;
      floor_num : out std_logic_vector(3 downto 0)
    );
  end component;

begin
  -- Instantiate the elevator_control entity
  UUT: elevator_control
    port map (
      clk       => clk,
      reset     => reset,
      floor_up  => floor_up,
      floor_down=> floor_down,
      floor_num => floor_num_out
    );

  -- Clock process
  process
  begin
    clk <= '0';
    wait for 5 ns;
    clk <= '1';
    wait for 5 ns;
  end process;

  -- Stimulus process
  process
  begin
    reset <= '1';
    floor_up <= '0';
    floor_down <= '0';
    wait for 10 ns;

    reset <= '0';
    wait for 10 ns;

    -- Test case 1: Move Up
    floor_up <= '1';
    wait for 10 ns;
    floor_up <= '0';
    wait for 10 ns;

    -- Test case 2: Move Down
    floor_down <= '1';
    wait for 10 ns;
    floor_down <= '0';
    wait for 10 ns;

    -- Test case 3: Stay Idle
    wait for 10 ns;

    -- Add more test cases as needed

    wait;
  end process;

end tb_architecture;

elevator_control/result.vcd
$date
  Sat Feb 10 11:04:19 2024
$end
$version
  GHDL v0
$end
$timescale
  1 fs
$end
$scope module standard $end
$upscope $end
$scope module std_logic_1164 $end
$upscope $end
$scope module numeric_std $end
$upscope $end
$scope module elevator_control_tb $end
$var reg 1 ! clk $end
$var reg 1 " reset $end
$var reg 1 # floor_up $end
$var reg 1 $ floor_down $end
$var reg 4 % floor_num_out[3:0] $end
$scope module uut $end
$var reg 1 & clk $end
$var reg 1 ' reset $end
$var reg 1 ( floor_up $end
$var reg 1 ) floor_down $end
$var reg 4 * floor_num[3:0] $end
$comment curr_state is not handled $end
$comment next_state is not handled $end
$var integer 32 + curr_floor $end
$upscope $end
$upscope $end
$enddefinitions $end
#0
0!
1"
0#
0$
b0000 %
0&
1'
0(
0)
b0000 *
b0 +
#5000000
1!
1&
#10000000
0!
0"
0&
0'
#15000000
1!
b0001 %
1&
b0001 *
b1 +
#20000000
0!
1#
0&
1(
#25000000
1!
b0010 %
1&
b0010 *
b10 +
#30000000
0!
0#
0&
0(
#35000000
1!
b0011 %
1&
b0011 *
b11 +
#40000000
0!
1$
0&
1)
#45000000
1!
b0100 %
1&
b0100 *
b100 +
#50000000
0!
0$
0&
0)
#55000000
1!
b0101 %
1&
b0101 *
b101 +
#60000000
0!
0&
#65000000
1!
b0110 %
1&
b0110 *
b110 +
#70000000
0!
0&
#75000000
1!
b0111 %
1&
b0111 *
b111 +
#80000000
0!
0&
#85000000
1!
b1000 %
1&
b1000 *
b1000 +
#90000000
0!
0&
#95000000
1!
b1001 %
1&
b1001 *
b1001 +
#100000000
0!
0&
#105000000
1!
b1010 %
1&
b1010 *
b1010 +
#110000000
0!
0&
#115000000
1!
b1011 %
1&
b1011 *
b1011 +
#120000000
0!
0&
#125000000
1!
b1100 %
1&
b1100 *
b1100 +
#130000000
0!
0&
#135000000
1!
b1101 %
1&
b1101 *
b1101 +
#140000000
0!
0&
#145000000
1!
b1110 %
1&
b1110 *
b1110 +
#150000000
0!
0&
#155000000
1!
b1111 %
1&
b1111 *
b1111 +
