full_adder/full_adder.vhdl
--VHDL code for a full adder using 2 half adder as a component
library IEEE;
use IEEE.STD_LOGIC_1164.ALL;
 
entity full_adder is
 Port ( A : in STD_LOGIC;
 B : in STD_LOGIC;
 Cin : in STD_LOGIC;
 S : out STD_LOGIC;
 Cout : out STD_LOGIC);
end full_adder;
 
architecture gate_level of full_adder is
 
begin
 
 S <= A XOR B XOR Cin ;
 Cout <= (A AND B) OR (Cin AND A) OR (Cin AND B) ;
 
end gate_level;

full_adder/full_adder_tb.vhdl

LIBRARY ieee;
USE ieee.std_logic_1164.ALL;
 
ENTITY tb_full_adder IS
END tb_full_adder;
 
ARCHITECTURE behavior OF tb_full_adder IS
 
 -- Component Declaration for the Unit Under Test (UUT)
 
 COMPONENT full_adder
 PORT(
 A : IN std_logic;
 B : IN std_logic;
 Cin : IN std_logic;
 S : OUT std_logic;
 Cout : OUT std_logic
 );
 END COMPONENT;
 
 --Inputs
 signal A : std_logic := '0';
 signal B : std_logic := '0';
 signal Cin : std_logic := '0';
 
 --Outputs
 signal S : std_logic;
 signal Cout : std_logic;
 
BEGIN
 
 -- Instantiate the Unit Under Test (UUT)
 uut: full_adder PORT MAP (
 A => A,
 B => B,
 Cin => Cin,
 S => S,
 Cout => Cout
 );
 
 -- Stimulus process
 stim_proc: process
 begin
 -- hold reset state for 100 ns.
 wait for 100 ns;
 
 -- insert stimulus here
 A <= '1';
 B <= '0';
 Cin <= '0';
 wait for 10 ns;
 
 A <= '0';
 B <= '1';
 Cin <= '0';
 wait for 10 ns;
 
 A <= '1';
 B <= '1';
 Cin <= '0';
 wait for 10 ns;
 
 A <= '0';
 B <= '0';
 Cin <= '1';
 wait for 10 ns;
 
 A <= '1';
 B <= '0';
 Cin <= '1';
 wait for 10 ns;
 
 A <= '0';
 B <= '1';
 Cin <= '1';
 wait for 10 ns;
 
 A <= '1';
 B <= '1';
 Cin <= '1';
 wait for 10 ns;
 
 end process;
 
END;

full_adder/result.vcd
$date
  Sat Feb 10 12:21:07 2024
$end
$version
  GHDL v0
$end
$timescale
  1 fs
$end
$scope module standard $end
$upscope $end
$scope module std_logic_1164 $end
$upscope $end
$scope module tb_full_adder $end
$var reg 1 ! a $end
$var reg 1 " b $end
$var reg 1 # cin $end
$var reg 1 $ s $end
$var reg 1 % cout $end
$scope module uut $end
$var reg 1 & a $end
$var reg 1 ' b $end
$var reg 1 ( cin $end
$var reg 1 ) s $end
$var reg 1 * cout $end
$upscope $end
$upscope $end
$enddefinitions $end
#0
0!
0"
0#
0$
0%
0&
0'
0(
0)
0*
#100000000
1!
1$
1&
1)
#110000000
0!
1"
0&
1'
#120000000
1!
0$
1%
1&
0)
1*
#130000000
0!
0"
1#
1$
0%
0&
0'
1(
1)
0*
#140000000
1!
0$
1%
1&
0)
1*
#150000000
0!
1"
0&
1'
#160000000
1!
1$
1&
1)
#170000000
#270000000
0"
0#
0%
0'
0(
0*
#280000000
0!
1"
0&
1'
#290000000
1!
0$
1%
1&
0)
1*
#300000000
0!
0"
1#
1$
0%
0&
0'
1(
1)
0*
#310000000
1!
0$
1%
1&
0)
1*
#320000000
0!
1"
0&
1'
#330000000
1!
1$
1&
1)
#340000000
#440000000
0"
0#
0%
0'
0(
0*
#450000000
0!
1"
0&
1'
#460000000
1!
0$
1%
1&
0)
1*
#470000000
0!
0"
1#
1$
0%
0&
0'
1(
1)
0*
#480000000
1!
0$
1%
1&
0)
1*
#490000000
0!
1"
0&
1'
#500000000
1!
1$
1&
1)
#510000000
#610000000
0"
0#
0%
0'
0(
0*
#620000000
0!
1"
0&
1'
#630000000
1!
0$
1%
1&
0)
1*
#640000000
0!
0"
1#
1$
0%
0&
0'
1(
1)
0*
#650000000
1!
0$
1%
1&
0)
1*
#660000000
0!
1"
0&
1'
#670000000
1!
1$
1&
1)
#680000000
#780000000
0"
0#
0%
0'
0(
0*
#790000000
0!
1"
0&
1'
#800000000
1!
0$
1%
1&
0)
1*
#810000000
0!
0"
1#
1$
0%
0&
0'
1(
1)
0*
#820000000
1!
0$
1%
1&
0)
1*
#830000000
0!
1"
0&
1'
#840000000
1!
1$
1&
1)
#850000000
#950000000
0"
0#
0%
0'
0(
0*
#960000000
0!
1"
0&
1'
#970000000
1!
0$
1%
1&
0)
1*
#980000000
0!
0"
1#
1$
0%
0&
0'
1(
1)
0*
#990000000
1!
0$
1%
1&
0)
1*
#1000000000
0!
1"
0&
1'
#1010000000
1!
1$
1&
1)
#1020000000
#1120000000
0"
0#
0%
0'
0(
0*
#1130000000
0!
1"
0&
1'
#1140000000
1!
0$
1%
1&
0)
1*
#1150000000
0!
0"
1#
1$
0%
0&
0'
1(
1)
0*
#1160000000
1!
0$
1%
1&
0)
1*
#1170000000
0!
1"
0&
1'
#1180000000
1!
1$
1&
1)
#1190000000
#1290000000
0"
0#
0%
0'
0(
0*
#1300000000
0!
1"
0&
1'
#1310000000
1!
0$
1%
1&
0)
1*
#1320000000
0!
0"
1#
1$
0%
0&
0'
1(
1)
0*
#1330000000
1!
0$
1%
1&
0)
1*
#1340000000
0!
1"
0&
1'
#1350000000
1!
1$
1&
1)
#1360000000
#1460000000
0"
0#
0%
0'
0(
0*
#1470000000
0!
1"
0&
1'
#1480000000
1!
0$
1%
1&
0)
1*
#1490000000
0!
0"
1#
1$
0%
0&
0'
1(
1)
0*
#1500000000
1!
0$
1%
1&
0)
1*
#1510000000
0!
1"
0&
1'
#1520000000
1!
1$
1&
1)
#1530000000
#1630000000
0"
0#
0%
0'
0(
0*
#1640000000
0!
1"
0&
1'
#1650000000
1!
0$
1%
1&
0)
1*
#1660000000
0!
0"
1#
1$
0%
0&
0'
1(
1)
0*
#1670000000
1!
0$
1%
1&
0)
1*
#1680000000
0!
1"
0&
1'
#1690000000
1!
1$
1&
1)
#1700000000
#1800000000
0"
0#
0%
0'
0(
0*
#1810000000
0!
1"
0&
1'
#1820000000
1!
0$
1%
1&
0)
1*
#1830000000
0!
0"
1#
1$
0%
0&
0'
1(
1)
0*
#1840000000
1!
0$
1%
1&
0)
1*
#1850000000
0!
1"
0&
1'
#1860000000
1!
1$
1&
1)
#1870000000
#1970000000
0"
0#
0%
0'
0(
0*
#1980000000
0!
1"
0&
1'
#1990000000
1!
0$
1%
1&
0)
1*
#2000000000
0!
0"
1#
1$
0%
0&
0'
1(
1)
0*
#2010000000
1!
0$
1%
1&
0)
1*
#2020000000
0!
1"
0&
1'
#2030000000
1!
1$
1&
1)
#2040000000
#2140000000
0"
0#
0%
0'
0(
0*
#2150000000
0!
1"
0&
1'
#2160000000
1!
0$
1%
1&
0)
1*
#2170000000
0!
0"
1#
1$
0%
0&
0'
1(
1)
0*
#2180000000
1!
0$
1%
1&
0)
1*
#2190000000
0!
1"
0&
1'
#2200000000
1!
1$
1&
1)
#2210000000
#2310000000
0"
0#
0%
0'
0(
0*
#2320000000
0!
1"
0&
1'
#2330000000
1!
0$
1%
1&
0)
1*
#2340000000
0!
0"
1#
1$
0%
0&
0'
1(
1)
0*
#2350000000
1!
0$
1%
1&
0)
1*
#2360000000
0!
1"
0&
1'
#2370000000
1!
1$
1&
1)
#2380000000
#2480000000
0"
0#
0%
0'
0(
0*
#2490000000
0!
1"
0&
1'
#2500000000
1!
0$
1%
1&
0)
1*
#2510000000
0!
0"
1#
1$
0%
0&
0'
1(
1)
0*
#2520000000
1!
0$
1%
1&
0)
1*
#2530000000
0!
1"
0&
1'
#2540000000
1!
1$
1&
1)
#2550000000
#2650000000
0"
0#
0%
0'
0(
0*
#2660000000
0!
1"
0&
1'
#2670000000
1!
0$
1%
1&
0)
1*
#2680000000
0!
0"
1#
1$
0%
0&
0'
1(
1)
0*
#2690000000
1!
0$
1%
1&
0)
1*
#2700000000
0!
1"
0&
1'
#2710000000
1!
1$
1&
1)
#2720000000
#2820000000
0"
0#
0%
0'
0(
0*
#2830000000
0!
1"
0&
1'
#2840000000
1!
0$
1%
1&
0)
1*
#2850000000
0!
0"
1#
1$
0%
0&
0'
1(
1)
0*
#2860000000
1!
0$
1%
1&
0)
1*
#2870000000
0!
1"
0&
1'
#2880000000
1!
1$
1&
1)
#2890000000
#2990000000
0"
0#
0%
0'
0(
0*
#3000000000
0!
1"
0&
1'
#3010000000
1!
0$
1%
1&
0)
1*
#3020000000
0!
0"
1#
1$
0%
0&
0'
1(
1)
0*
#3030000000
1!
0$
1%
1&
0)
1*
#3040000000
0!
1"
0&
1'
#3050000000
1!
1$
1&
1)
#3060000000
#3160000000
0"
0#
0%
0'
0(
0*
#3170000000
0!
1"
0&
1'
#3180000000
1!
0$
1%
1&
0)
1*
#3190000000
0!
0"
1#
1$
0%
0&
0'
1(
1)
0*
#3200000000
1!
0$
1%
1&
0)
1*
#3210000000
0!
1"
0&
1'
#3220000000
1!
1$
1&
1)
#3230000000
#3330000000
0"
0#
0%
0'
0(
0*
#3340000000
0!
1"
0&
1'
#3350000000
1!
0$
1%
1&
0)
1*
#3360000000
0!
0"
1#
1$
0%
0&
0'
1(
1)
0*
#3370000000
1!
0$
1%
1&
0)
1*
#3380000000
0!
1"
0&
1'
#3390000000
1!
1$
1&
1)
#3400000000
#3500000000
0"
0#
0%
0'
0(
0*
#3510000000
0!
1"
0&
1'
#3520000000
1!
0$
1%
1&
0)
1*
#3530000000
0!
0"
1#
1$
0%
0&
0'
1(
1)
0*
#3540000000
1!
0$
1%
1&
0)
1*
#3550000000
0!
1"
0&
1'
#3560000000
1!
1$
1&
1)
#3570000000
#3670000000
0"
0#
0%
0'
0(
0*
#3680000000
0!
1"
0&
1'
#3690000000
1!
0$
1%
1&
0)
1*
#3700000000
0!
0"
1#
1$
0%
0&
0'
1(
1)
0*
#3710000000
1!
0$
1%
1&
0)
1*
#3720000000
0!
1"
0&
1'
#3730000000
1!
1$
1&
1)
#3740000000
#3840000000
0"
0#
0%
0'
0(
0*
#3850000000
0!
1"
0&
1'
#3860000000
1!
0$
1%
1&
0)
1*
#3870000000
0!
0"
1#
1$
0%
0&
0'
1(
1)
0*
#3880000000
1!
0$
1%
1&
0)
1*
#3890000000
0!
1"
0&
1'
#3900000000
1!
1$
1&
1)
#3910000000
#4010000000
0"
0#
0%
0'
0(
0*
#4020000000
0!
1"
0&
1'
#4030000000
1!
0$
1%
1&
0)
1*
#4040000000
0!
0"
1#
1$
0%
0&
0'
1(
1)
0*
#4050000000
1!
0$
1%
1&
0)
1*
#4060000000
0!
1"
0&
1'
#4070000000
1!
1$
1&
1)
#4080000000
#4180000000
0"
0#
0%
0'
0(
0*
#4190000000
0!
1"
0&
1'
#4200000000
1!
0$
1%
1&
0)
1*
#4210000000
0!
0"
1#
1$
0%
0&
0'
1(
1)
0*
#4220000000
1!
0$
1%
1&
0)
1*
#4230000000
0!
1"
0&
1'
#4240000000
1!
1$
1&
1)
#4250000000
#4350000000
0"
0#
0%
0'
0(
0*
#4360000000
0!
1"
0&
1'
#4370000000
1!
0$
1%
1&
0)
1*
#4380000000
0!
0"
1#
1$
0%
0&
0'
1(
1)
0*
#4390000000
1!
0$
1%
1&
0)
1*
#4400000000
0!
1"
0&
1'
#4410000000
1!
1$
1&
1)
#4420000000
#4520000000
0"
0#
0%
0'
0(
0*
#4530000000
0!
1"
0&
1'
#4540000000
1!
0$
1%
1&
0)
1*
#4550000000
0!
0"
1#
1$
0%
0&
0'
1(
1)
0*
#4560000000
1!
0$
1%
1&
0)
1*
#4570000000
0!
1"
0&
1'
#4580000000
1!
1$
1&
1)
#4590000000
#4690000000
0"
0#
0%
0'
0(
0*
#4700000000
0!
1"
0&
1'
#4710000000
1!
0$
1%
1&
0)
1*
#4720000000
0!
0"
1#
1$
0%
0&
0'
1(
1)
0*
#4730000000
1!
0$
1%
1&
0)
1*
#4740000000
0!
1"
0&
1'
#4750000000
1!
1$
1&
1)
#4760000000
#4860000000
0"
0#
0%
0'
0(
0*
#4870000000
0!
1"
0&
1'
#4880000000
1!
0$
1%
1&
0)
1*
#4890000000
0!
0"
1#
1$
0%
0&
0'
1(
1)
0*
#4900000000
1!
0$
1%
1&
0)
1*
#4910000000
0!
1"
0&
1'
#4920000000
1!
1$
1&
1)
#4930000000
#5030000000
0"
0#
0%
0'
0(
0*
#5040000000
0!
1"
0&
1'
#5050000000
1!
0$
1%
1&
0)
1*
#5060000000
0!
0"
1#
1$
0%
0&
0'
1(
1)
0*
#5070000000
1!
0$
1%
1&
0)
1*
#5080000000
0!
1"
0&
1'
#5090000000
1!
1$
1&
1)
#5100000000
#5200000000
0"
0#
0%
0'
0(
0*
#5210000000
0!
1"
0&
1'
#5220000000
1!
0$
1%
1&
0)
1*
#5230000000
0!
0"
1#
1$
0%
0&
0'
1(
1)
0*
#5240000000
1!
0$
1%
1&
0)
1*
#5250000000
0!
1"
0&
1'
#5260000000
1!
1$
1&
1)
#5270000000
#5370000000
0"
0#
0%
0'
0(
0*
#5380000000
0!
1"
0&
1'
#5390000000
1!
0$
1%
1&
0)
1*
#5400000000
0!
0"
1#
1$
0%
0&
0'
1(
1)
0*
#5410000000
1!
0$
1%
1&
0)
1*
#5420000000
0!
1"
0&
1'
#5430000000
1!
1$
1&
1)
#5440000000
#5540000000
0"
0#
0%
0'
0(
0*
#5550000000
0!
1"
0&
1'
#5560000000
1!
0$
1%
1&
0)
1*
#5570000000
0!
0"
1#
1$
0%
0&
0'
1(
1)
0*
#5580000000
1!
0$
1%
1&
0)
1*
#5590000000
0!
1"
0&
1'
#5600000000
1!
1$
1&
1)
#5610000000
#5710000000
0"
0#
0%
0'
0(
0*
#5720000000
0!
1"
0&
1'
#5730000000
1!
0$
1%
1&
0)
1*
#5740000000
0!
0"
1#
1$
0%
0&
0'
1(
1)
0*
#5750000000
1!
0$
1%
1&
0)
1*
#5760000000
0!
1"
0&
1'
#5770000000
1!
1$
1&
1)
#5780000000
#5880000000
0"
0#
0%
0'
0(
0*
#5890000000
0!
1"
0&
1'
#5900000000
1!
0$
1%
1&
0)
1*
#5910000000
0!
0"
1#
1$
0%
0&
0'
1(
1)
0*
#5920000000
1!
0$
1%
1&
0)
1*
#5930000000
0!
1"
0&
1'
#5940000000
1!
1$
1&
1)
#5950000000
#6050000000
0"
0#
0%
0'
0(
0*
#6060000000
0!
1"
0&
1'
#6070000000
1!
0$
1%
1&
0)
1*
#6080000000
0!
0"
1#
1$
0%
0&
0'
1(
1)
0*
#6090000000
1!
0$
1%
1&
0)
1*
#6100000000
0!
1"
0&
1'
#6110000000
1!
1$
1&
1)
#6120000000
#6220000000
0"
0#
0%
0'
0(
0*
#6230000000
0!
1"
0&
1'
#6240000000
1!
0$
1%
1&
0)
1*
#6250000000
0!
0"
1#
1$
0%
0&
0'
1(
1)
0*
#6260000000
1!
0$
1%
1&
0)
1*
#6270000000
0!
1"
0&
1'
#6280000000
1!
1$
1&
1)
#6290000000
#6390000000
0"
0#
0%
0'
0(
0*
#6400000000
0!
1"
0&
1'
#6410000000
1!
0$
1%
1&
0)
1*
#6420000000
0!
0"
1#
1$
0%
0&
0'
1(
1)
0*
#6430000000
1!
0$
1%
1&
0)
1*
#6440000000
0!
1"
0&
1'
#6450000000
1!
1$
1&
1)
#6460000000
#6560000000
0"
0#
0%
0'
0(
0*
#6570000000
0!
1"
0&
1'
#6580000000
1!
0$
1%
1&
0)
1*
#6590000000
0!
0"
1#
1$
0%
0&
0'
1(
1)
0*
#6600000000
1!
0$
1%
1&
0)
1*
#6610000000
0!
1"
0&
1'
#6620000000
1!
1$
1&
1)
#6630000000
#6730000000
0"
0#
0%
0'
0(
0*
#6740000000
0!
1"
0&
1'
#6750000000
1!
0$
1%
1&
0)
1*
#6760000000
0!
0"
1#
1$
0%
0&
0'
1(
1)
0*
#6770000000
1!
0$
1%
1&
0)
1*
#6780000000
0!
1"
0&
1'
#6790000000
1!
1$
1&
1)
#6800000000
#6900000000
0"
0#
0%
0'
0(
0*
#6910000000
0!
1"
0&
1'
#6920000000
1!
0$
1%
1&
0)
1*
#6930000000
0!
0"
1#
1$
0%
0&
0'
1(
1)
0*
#6940000000
1!
0$
1%
1&
0)
1*
#6950000000
0!
1"
0&
1'
#6960000000
1!
1$
1&
1)
#6970000000
#7070000000
0"
0#
0%
0'
0(
0*
#7080000000
0!
1"
0&
1'
#7090000000
1!
0$
1%
1&
0)
1*
#7100000000
0!
0"
1#
1$
0%
0&
0'
1(
1)
0*
#7110000000
1!
0$
1%
1&
0)
1*
#7120000000
0!
1"
0&
1'
#7130000000
1!
1$
1&
1)
#7140000000
#7240000000
0"
0#
0%
0'
0(
0*
#7250000000
0!
1"
0&
1'
#7260000000
1!
0$
1%
1&
0)
1*
#7270000000
0!
0"
1#
1$
0%
0&
0'
1(
1)
0*
#7280000000
1!
0$
1%
1&
0)
1*
#7290000000
0!
1"
0&
1'
#7300000000
1!
1$
1&
1)
#7310000000
#7410000000
0"
0#
0%
0'
0(
0*
#7420000000
0!
1"
0&
1'
#7430000000
1!
0$
1%
1&
0)
1*
#7440000000
0!
0"
1#
1$
0%
0&
0'
1(
1)
0*
#7450000000
1!
0$
1%
1&
0)
1*
#7460000000
0!
1"
0&
1'
#7470000000
1!
1$
1&
1)
#7480000000
#7580000000
0"
0#
0%
0'
0(
0*
#7590000000
0!
1"
0&
1'
#7600000000
1!
0$
1%
1&
0)
1*
#7610000000
0!
0"
1#
1$
0%
0&
0'
1(
1)
0*
#7620000000
1!
0$
1%
1&
0)
1*
#7630000000
0!
1"
0&
1'
#7640000000
1!
1$
1&
1)
#7650000000
#7750000000
0"
0#
0%
0'
0(
0*
#7760000000
0!
1"
0&
1'
#7770000000
1!
0$
1%
1&
0)
1*
#7780000000
0!
0"
1#
1$
0%
0&
0'
1(
1)
0*
#7790000000
1!
0$
1%
1&
0)
1*
#7800000000
0!
1"
0&
1'
#7810000000
1!
1$
1&
1)
#7820000000
#7920000000
0"
0#
0%
0'
0(
0*
#7930000000
0!
1"
0&
1'
#7940000000
1!
0$
1%
1&
0)
1*
#7950000000
0!
0"
1#
1$
0%
0&
0'
1(
1)
0*
#7960000000
1!
0$
1%
1&
0)
1*
#7970000000
0!
1"
0&
1'
#7980000000
1!
1$
1&
1)
#7990000000
#8090000000
0"
0#
0%
0'
0(
0*
#8100000000
0!
1"
0&
1'
#8110000000
1!
0$
1%
1&
0)
1*
#8120000000
0!
0"
1#
1$
0%
0&
0'
1(
1)
0*
#8130000000
1!
0$
1%
1&
0)
1*
#8140000000
0!
1"
0&
1'
#8150000000
1!
1$
1&
1)
#8160000000
#8260000000
0"
0#
0%
0'
0(
0*
#8270000000
0!
1"
0&
1'
#8280000000
1!
0$
1%
1&
0)
1*
#8290000000
0!
0"
1#
1$
0%
0&
0'
1(
1)
0*
#8300000000
1!
0$
1%
1&
0)
1*
#8310000000
0!
1"
0&
1'
#8320000000
1!
1$
1&
1)
#8330000000
#8430000000
0"
0#
0%
0'
0(
0*
#8440000000
0!
1"
0&
1'
#8450000000
1!
0$
1%
1&
0)
1*
#8460000000
0!
0"
1#
1$
0%
0&
0'
1(
1)
0*
#8470000000
1!
0$
1%
1&
0)
1*
#8480000000
0!
1"
0&
1'
#8490000000
1!
1$
1&
1)
#8500000000
#8600000000
0"
0#
0%
0'
0(
0*
#8610000000
0!
1"
0&
1'
#8620000000
1!
0$
1%
1&
0)
1*
#8630000000
0!
0"
1#
1$
0%
0&
0'
1(
1)
0*
#8640000000
1!
0$
1%
1&
0)
1*
#8650000000
0!
1"
0&
1'
#8660000000
1!
1$
1&
1)
#8670000000
#8770000000
0"
0#
0%
0'
0(
0*
#8780000000
0!
1"
0&
1'
#8790000000
1!
0$
1%
1&
0)
1*
#8800000000
0!
0"
1#
1$
0%
0&
0'
1(
1)
0*
#8810000000
1!
0$
1%
1&
0)
1*
#8820000000
0!
1"
0&
1'
#8830000000
1!
1$
1&
1)
#8840000000
#8940000000
0"
0#
0%
0'
0(
0*
#8950000000
0!
1"
0&
1'
#8960000000
1!
0$
1%
1&
0)
1*
#8970000000
0!
0"
1#
1$
0%
0&
0'
1(
1)
0*
#8980000000
1!
0$
1%
1&
0)
1*
#8990000000
0!
1"
0&
1'
#9000000000
1!
1$
1&
1)
#9010000000
#9110000000
0"
0#
0%
0'
0(
0*
#9120000000
0!
1"
0&
1'
#9130000000
1!
0$
1%
1&
0)
1*
#9140000000
0!
0"
1#
1$
0%
0&
0'
1(
1)
0*
#9150000000
1!
0$
1%
1&
0)
1*
#9160000000
0!
1"
0&
1'
#9170000000
1!
1$
1&
1)
#9180000000
#9280000000
0"
0#
0%
0'
0(
0*
#9290000000
0!
1"
0&
1'
#9300000000
1!
0$
1%
1&
0)
1*
#9310000000
0!
0"
1#
1$
0%
0&
0'
1(
1)
0*
#9320000000
1!
0$
1%
1&
0)
1*
#9330000000
0!
1"
0&
1'
#9340000000
1!
1$
1&
1)
#9350000000
#9450000000
0"
0#
0%
0'
0(
0*
#9460000000
0!
1"
0&
1'
#9470000000
1!
0$
1%
1&
0)
1*
#9480000000
0!
0"
1#
1$
0%
0&
0'
1(
1)
0*
#9490000000
1!
0$
1%
1&
0)
1*
#9500000000
0!
1"
0&
1'
#9510000000
1!
1$
1&
1)
#9520000000
#9620000000
0"
0#
0%
0'
0(
0*
#9630000000
0!
1"
0&
1'
#9640000000
1!
0$
1%
1&
0)
1*
#9650000000
0!
0"
1#
1$
0%
0&
0'
1(
1)
0*
#9660000000
1!
0$
1%
1&
0)
1*
#9670000000
0!
1"
0&
1'
#9680000000
1!
1$
1&
1)
#9690000000
#9790000000
0"
0#
0%
0'
0(
0*
#9800000000
0!
1"
0&
1'
#9810000000
1!
0$
1%
1&
0)
1*
#9820000000
0!
0"
1#
1$
0%
0&
0'
1(
1)
0*
#9830000000
1!
0$
1%
1&
0)
1*
#9840000000
0!
1"
0&
1'
#9850000000
1!
1$
1&
1)
#9860000000
#9960000000
0"
0#
0%
0'
0(
0*
#9970000000
0!
1"
0&
1'
#9980000000
1!
0$
1%
1&
0)
1*
#9990000000
0!
0"
1#
1$
0%
0&
0'
1(
1)
0*
#10000000000
1!
0$
1%
1&
0)
1*
#10010000000
0!
1"
0&
1'
#10020000000
1!
1$
1&
1)
#10030000000
#10130000000
0"
0#
0%
0'
0(
0*
#10140000000
0!
1"
0&
1'
#10150000000
1!
0$
1%
1&
0)
1*
#10160000000
0!
0"
1#
1$
0%
0&
0'
1(
1)
0*
#10170000000
1!
0$
1%
1&
0)
1*
#10180000000
0!
1"
0&
1'
#10190000000
1!
1$
1&
1)
#10200000000
#10300000000
0"
0#
0%
0'
0(
0*
#10310000000
0!
1"
0&
1'
#10320000000
1!
0$
1%
1&
0)
1*
#10330000000
0!
0"
1#
1$
0%
0&
0'
1(
1)
0*
#10340000000
1!
0$
1%
1&
0)
1*
#10350000000
0!
1"
0&
1'
#10360000000
1!
1$
1&
1)
#10370000000
#10470000000
0"
0#
0%
0'
0(
0*
#10480000000
0!
1"
0&
1'
#10490000000
1!
0$
1%
1&
0)
1*
#10500000000
0!
0"
1#
1$
0%
0&
0'
1(
1)
0*
#10510000000
1!
0$
1%
1&
0)
1*
#10520000000
0!
1"
0&
1'
#10530000000
1!
1$
1&
1)
#10540000000
#10640000000
0"
0#
0%
0'
0(
0*
#10650000000
0!
1"
0&
1'
#10660000000
1!
0$
1%
1&
0)
1*
#10670000000
0!
0"
1#
1$
0%
0&
0'
1(
1)
0*
#10680000000
1!
0$
1%
1&
0)
1*
#10690000000
0!
1"
0&
1'
#10700000000
1!
1$
1&
1)
#10710000000
#10810000000
0"
0#
0%
0'
0(
0*
#10820000000
0!
1"
0&
1'
#10830000000
1!
0$
1%
1&
0)
1*
#10840000000
0!
0"
1#
1$
0%
0&
0'
1(
1)
0*
#10850000000
1!
0$
1%
1&
0)
1*
#10860000000
0!
1"
0&
1'
#10870000000
1!
1$
1&
1)
#10880000000
#10980000000
0"
0#
0%
0'
0(
0*
#10990000000
0!
1"
0&
1'
#11000000000
1!
0$
1%
1&
0)
1*
#11010000000
0!
0"
1#
1$
0%
0&
0'
1(
1)
0*
#11020000000
1!
0$
1%
1&
0)
1*
#11030000000
0!
1"
0&
1'
#11040000000
1!
1$
1&
1)
#11050000000
#11150000000
0"
0#
0%
0'
0(
0*
#11160000000
0!
1"
0&
1'
#11170000000
1!
0$
1%
1&
0)
1*
#11180000000
0!
0"
1#
1$
0%
0&
0'
1(
1)
0*
#11190000000
1!
0$
1%
1&
0)
1*
#11200000000
0!
1"
0&
1'
#11210000000
1!
1$
1&
1)
#11220000000
#11320000000
0"
0#
0%
0'
0(
0*
#11330000000
0!
1"
0&
1'
#11340000000
1!
0$
1%
1&
0)
1*
#11350000000
0!
0"
1#
1$
0%
0&
0'
1(
1)
0*
#11360000000
1!
0$
1%
1&
0)
1*
#11370000000
0!
1"
0&
1'
#11380000000
1!
1$
1&
1)
#11390000000
#11490000000
0"
0#
0%
0'
0(
0*
#11500000000
0!
1"
0&
1'
#11510000000
1!
0$
1%
1&
0)
1*
#11520000000
0!
0"
1#
1$
0%
0&
0'
1(
1)
0*
#11530000000
1!
0$
1%
1&
0)
1*
#11540000000
0!
1"
0&
1'
#11550000000
1!
1$
1&
1)
#11560000000
#11660000000
0"
0#
0%
0'
0(
0*
#11670000000
0!
1"
0&
1'
#11680000000
1!
0$
1%
1&
0)
1*
#11690000000
0!
0"
1#
1$
0%
0&
0'
1(
1)
0*
#11700000000
1!
0$
1%
1&
0)
1*
#11710000000
0!
1"
0&
1'
#11720000000
1!
1$
1&
1)
#11730000000
#11830000000
0"
0#
0%
0'
0(
0*
#11840000000
0!
1"
0&
1'
#11850000000
1!
0$
1%
1&
0)
1*
#11860000000
0!
0"
1#
1$
0%
0&
0'
1(
1)
0*
#11870000000
1!
0$
1%
1&
0)
1*
#11880000000
0!
1"
0&
1'
#11890000000
1!
1$
1&
1)
#11900000000
#12000000000
0"
0#
0%
0'
0(
0*
#12010000000
0!
1"
0&
1'
#12020000000
1!
0$
1%
1&
0)
1*
#12030000000
0!
0"
1#
1$
0%
0&
0'
1(
1)
0*
#12040000000
1!
0$
1%
1&
0)
1*
#12050000000
0!
1"
0&
1'
#12060000000
1!
1$
1&
1)
#12070000000
#12170000000
0"
0#
0%
0'
0(
0*
#12180000000
0!
1"
0&
1'
#12190000000
1!
0$
1%
1&
0)
1*
#12200000000
0!
0"
1#
1$
0%
0&
0'
1(
1)
0*
#12210000000
1!
0$
1%
1&
0)
1*
#12220000000
0!
1"
0&
1'
#12230000000
1!
1$
1&
1)
#12240000000
#12340000000
0"
0#
0%
0'
0(
0*
#12350000000
0!
1"
0&
1'
#12360000000
1!
0$
1%
1&
0)
1*
#12370000000
0!
0"
1#
1$
0%
0&
0'
1(
1)
0*
#12380000000
1!
0$
1%
1&
0)
1*
#12390000000
0!
1"
0&
1'
#12400000000
1!
1$
1&
1)
#12410000000
#12510000000
0"
0#
0%
0'
0(
0*
#12520000000
0!
1"
0&
1'
#12530000000
1!
0$
1%
1&
0)
1*
#12540000000
0!
0"
1#
1$
0%
0&
0'
1(
1)
0*
#12550000000
1!
0$
1%
1&
0)
1*
#12560000000
0!
1"
0&
1'
#12570000000
1!
1$
1&
1)
#12580000000
#12680000000
0"
0#
0%
0'
0(
0*
#12690000000
0!
1"
0&
1'
#12700000000
1!
0$
1%
1&
0)
1*
#12710000000
0!
0"
1#
1$
0%
0&
0'
1(
1)
0*
#12720000000
1!
0$
1%
1&
0)
1*
#12730000000
0!
1"
0&
1'
#12740000000
1!
1$
1&
1)
#12750000000
#12850000000
0"
0#
0%
0'
0(
0*
#12860000000
0!
1"
0&
1'
#12870000000
1!
0$
1%
1&
0)
1*
#12880000000
0!
0"
1#
1$
0%
0&
0'
1(
1)
0*
#12890000000
1!
0$
1%
1&
0)
1*
#12900000000
0!
1"
0&
1'
#12910000000
1!
1$
1&
1)
#12920000000
#13020000000
0"
0#
0%
0'
0(
0*
#13030000000
0!
1"
0&
1'
#13040000000
1!
0$
1%
1&
0)
1*
#13050000000
0!
0"
1#
1$
0%
0&
0'
1(
1)
0*
#13060000000
1!
0$
1%
1&
0)
1*
#13070000000
0!
1"
0&
1'
#13080000000
1!
1$
1&
1)
#13090000000
#13190000000
0"
0#
0%
0'
0(
0*
#13200000000
0!
1"
0&
1'
#13210000000
1!
0$
1%
1&
0)
1*
#13220000000
0!
0"
1#
1$
0%
0&
0'
1(
1)
0*
#13230000000
1!
0$
1%
1&
0)
1*
#13240000000
0!
1"
0&
1'
#13250000000
1!
1$
1&
1)
#13260000000
#13360000000
0"
0#
0%
0'
0(
0*
#13370000000
0!
1"
0&
1'
#13380000000
1!
0$
1%
1&
0)
1*
#13390000000
0!
0"
1#
1$
0%
0&
0'
1(
1)
0*
#13400000000
1!
0$
1%
1&
0)
1*
#13410000000
0!
1"
0&
1'
#13420000000
1!
1$
1&
1)
#13430000000
#13530000000
0"
0#
0%
0'
0(
0*
#13540000000
0!
1"
0&
1'
#13550000000
1!
0$
1%
1&
0)
1*
#13560000000
0!
0"
1#
1$
0%
0&
0'
1(
1)
0*
#13570000000
1!
0$
1%
1&
0)
1*
#13580000000
0!
1"
0&
1'
#13590000000
1!
1$
1&
1)
#13600000000
#13700000000
0"
0#
0%
0'
0(
0*
#13710000000
0!
1"
0&
1'
#13720000000
1!
0$
1%
1&
0)
1*
#13730000000
0!
0"
1#
1$
0%
0&
0'
1(
1)
0*
#13740000000
1!
0$
1%
1&
0)
1*
#13750000000
0!
1"
0&
1'
#13760000000
1!
1$
1&
1)
#13770000000
#13870000000
0"
0#
0%
0'
0(
0*
#13880000000
0!
1"
0&
1'
#13890000000
1!
0$
1%
1&
0)
1*
#13900000000
0!
0"
1#
1$
0%
0&
0'
1(
1)
0*
#13910000000
1!
0$
1%
1&
0)
1*
